scalar_py/__init__.py
scalar_docs-0.1.2.dist-info/METADATA
scalar_docs-0.1.2.dist-info/WHEEL
scalar_docs-0.1.2.dist-info/top_level.txt
scalar_docs-0.1.2.dist-info/RECORD
