Metadata-Version: 2.2
Name: scalar-docs
Version: 0.1.2
Summary: A Python wrapper for the Scalar API documentation library.
Home-page: https://github.com/OscarRG/scalar-py
Author: Oscar Rivas
Author-email: Oscar Rivas <80918302+OscarRG@noreply.users.github.com>
Project-URL: Homepage, https://github.com/OscarRG/scalar-py
Project-URL: Documentation, https://github.com/OscarRG/scalar-py
Project-URL: Repository, https://github.com/OscarRG/scalar-py
Requires-Dist: requests
Provides-Extra: django-example
Requires-Dist: django; extra == "django-example"
Provides-Extra: fastapi-example
Requires-Dist: fastapi; extra == "fastapi-example"
Provides-Extra: flask-example
Requires-Dist: flask; extra == "flask-example"
Dynamic: author
Dynamic: home-page
